{
  "comments": [
    {
      "name": "수학열공",
      "thumbnail": "assets/images/thumbnail.jpg",
      "schoolName": "화덕중학교",
      "grade": 3,
      "elapsedTime": 60000,
      "content": "출석 체크요!"
    },
    {
      "name": "Jo B",
      "thumbnail": "assets/images/thumbnail.jpg",
      "schoolName": "여수중학교",
      "grade": 1,
      "elapsedTime": 120000,
      "content": "정수와 유리수에서 3번 문제 모르겠네요."
    },
    {
      "name": "Jo B",
      "thumbnail": "assets/images/bag01.png",
      "schoolName": "여수중학교",
      "grade": 1,
      "elapsedTime": 10000,
      "content": "밥먹고 합시다!"
    },
    {
      "name": "Jo B",
      "thumbnail": "assets/images/thumbnail.jpg",
      "schoolName": "여수중학교",
      "grade": 1,
      "elapsedTime": 1200000,
      "content": "거지왕자인가"
    },
    {
      "name": "Jo B",
      "thumbnail": "assets/images/thumbnail.jpg",
      "schoolName": "여수중학교",
      "grade": 1,
      "elapsedTime": 200000,
      "content": "근데 낙사가 없으니까 페르시아 하는 맛이 안 난다고 하던 사람도 꽤 많던 아이러니함이...ㅋㅋㅋㅋㅋ"
    },
    {
      "name": "Jo B",
      "thumbnail": "assets/images/thumbnail.jpg",
      "schoolName": "여수중학교",
      "grade": 1,
      "elapsedTime": 1200000,
      "content": "그 플삼이랑 삼돌이로 나온 그건가! 나름 잼게했는데"
    },
    {
      "name": "Jo B",
      "thumbnail": "assets/images/thumbnail.jpg",
      "schoolName": "여수중학교",
      "grade": 1,
      "elapsedTime": 1200000,
      "content": "최신기기로도 할수있고요."
    },
    {
      "name": "Jo B",
      "thumbnail": "assets/images/thumbnail.jpg",
      "schoolName": "여수중학교",
      "grade": 1,
      "elapsedTime": 1200000,
      "content": "FORWARD 세일 때 끼워 사서 얼마에 샀지 보니 630원에 샀네요.\nFORWARD가 할인 참 좋았죠."
    },
    {
      "name": "Jo B",
      "thumbnail": "assets/images/thumbnail.jpg",
      "schoolName": "여수중학교",
      "grade": 1,
      "elapsedTime": 1200000,
      "content": "세월을 비교적 덜타는 렌더링 방식이라 비주얼도 볼만하고\n낙사 같은 스트레스가 없어서 힐링하며 스토리 쭉 밀기 좋은 게임입니다."
    },
    {
      "name": "Jo B",
      "thumbnail": "assets/images/thumbnail.jpg",
      "schoolName": "여수중학교",
      "grade": 1,
      "elapsedTime": 1200000,
      "content": "이 앞전작들은 플스2 시기에 나와서 다이렉트 인풋이 적용되는데 이 작품은 엑스박스 360시기에 나와서 x input 적용입니다. \n게임 패드 플레이하는데 큰 지장은 없을겁니다."
    }
  ]
}

